{"notifications": [{"item": {"unreadCount": 0}, "type": "notificationTray"}], "meta": {"code": 200}, "response": {"venue": {"rating": 9.31, "reasons": {"count": 1, "items": [{"count": 2, "target": {"object": {"ignorable": false, "type": "social", "id": "53c55765498e0bc64c2bd5da", "target": {"url": "/venues/4a1c8506f964a520457b1fe3/social", "type": "path"}}, "type": "navigation"}, "summary": "2 friends have been here", "reasonName": "friendAndSelfCheckinReason", "message": "Tam\u00e1s V. and Bal\u00e1zs D. have been here", "type": "social"}]}, "likes": {"count": 465, "groups": [{"count": 465, "items": [], "type": "others"}], "summary": "465 likes"}, "id": "4a1c8506f964a520457b1fe3", "createdAt": 1243383046, "description": "Hinweis: \r\nBitte beachten Sie, dass Sie durch Ihren Check-in und das Erreichen des Mayor-Status an diesem Bahnhof ab 30.11.2012 auf unserer Facebook-Page unter https://www.facebook.com/deutschebahn/app_309524899161709 angezeigt werden. \r\n\r\nImpressum: \r\nhttp://www.deutschebahn.com/impressum", "verified": true, "hereNow": {"count": 18, "groups": [{"count": 18, "items": [], "type": "others", "name": "Other people here"}], "summary": "18 people here"}, "mayor": {"count": 0}, "shortUrl": "http://4sq.com/6VxowW", "pageUpdates": {"count": 7, "items": []}, "location": {"city": "Berlin", "cc": "DE", "country": "Deutschland", "postalCode": "10557", "state": "Berlin", "formattedAddress": ["Europaplatz 1 (Washingtonplatz)", "10557 Berlin", "Deutschland"], "crossStreet": "Washingtonplatz", "address": "Europaplatz 1", "lat": 52.52490343170594, "lng": 13.3693528175354}, "dislike": false, "listed": {"count": 413, "groups": [{"count": 413, "items": [{"description": "", "collaborative": false, "url": "/petebrightside/list/must-dos-in-berlin", "photo": {"suffix": "/QDT0CQCQ3EQJ5CG5KGLULRICJJGSCLLHB4MZULEWPTXAWBR4.jpg", "visibility": "public", "height": 480, "width": 720, "prefix": "https://irs1.4sqi.net/img/general/", "user": {"lastName": "Fehrmann", "photo": {"prefix": "https://irs0.4sqi.net/img/user/", "suffix": "/FMMRJYTUYTAGAVNA.jpg"}, "id": "2923307", "firstName": "Andr\u00e9", "gender": "male"}, "id": "4ed10482b634dd299237112f", "createdAt": 1322321026}, "editable": false, "listItems": {"count": 178, "items": [{"photo": {"suffix": "/LP1J332A2MQIKOUD0QDBTKITDDUDTFGDFFH5SEQ4WOKJZM4Y.jpg", "visibility": "public", "height": 720, "width": 540, "prefix": "https://irs3.4sqi.net/img/general/", "user": {"lastName": "Reinberger", "photo": {"prefix": "https://irs3.4sqi.net/img/user/", "suffix": "/UQEJGCHIYXOMXJKZ.jpg"}, "id": "292456", "firstName": "Hannes", "gender": "male"}, "id": "4ecbdd48469068520c6ce047", "createdAt": 1321983304}, "id": "v4a1c8506f964a520457b1fe3", "createdAt": 1324844392}]}, "createdAt": 1324844123, "public": true, "followers": {"count": 631}, "user": {"lastName": "Csakvari", "photo": {"prefix": "https://irs1.4sqi.net/img/user/", "suffix": "/BH30PZDL3XLNAZS2.jpg"}, "id": "4680973", "firstName": "Peter", "gender": "male"}, "updatedAt": 1399889943, "type": "others", "id": "4ef7845b6da1f7b6611ab18f", "canonicalUrl": "https://foursquare.com/petebrightside/list/must-dos-in-berlin", "name": "Must Do's in Berlin"}, {"description": "Ab sofort erhalten Sie an diesen Bahnh\u00f6fen 30 Minuten kostenloses WLAN.\nDanach stehen zur weiteren Nutzung Tarife der Telekom zur Verf\u00fcgung.\nTarifinformationen finden Sie unter www.hotspot.de.", "collaborative": false, "url": "/deutschebahn/list/wlan-bahnh%C3%B6fe", "photo": {"suffix": "/21669589_nRnpmiZOiTPfhX1B3SDOCajrY2-OyXoLnVMJgxsZmzc.jpg", "visibility": "public", "height": 277, "width": 278, "prefix": "https://irs0.4sqi.net/img/general/", "user": {"gender": "none", "type": "chain", "id": "21669589", "firstName": "Deutsche Bahn", "photo": {"prefix": "https://irs3.4sqi.net/img/user/", "suffix": "/OCYMLBV1WLVUDZBG.jpg"}}, "id": "5242bbf52fc69ae3e7fd59ed", "createdAt": 1380105205}, "logView": true, "editable": false, "listItems": {"count": 105, "items": [{"photo": {"suffix": "/21669589_cYUUbcj-79d4BdqYpr9eUe3wSawRVvIFM-4ZmBbgork.png", "visibility": "public", "height": 622, "width": 929, "prefix": "https://irs2.4sqi.net/img/general/", "user": {"gender": "none", "type": "chain", "id": "21669589", "firstName": "Deutsche Bahn", "photo": {"prefix": "https://irs3.4sqi.net/img/user/", "suffix": "/OCYMLBV1WLVUDZBG.jpg"}}, "id": "510bbef2183fc1f8f3600b89", "createdAt": 1359724274}, "id": "v4a1c8506f964a520457b1fe3", "createdAt": 1380105715}]}, "createdAt": 1380098635, "public": true, "entities": [{"indices": [177, 191], "object": {"url": "http://www.hotspot.de"}, "type": "url"}], "followers": {"count": 289}, "user": {"gender": "none", "type": "chain", "id": "21669589", "firstName": "Deutsche Bahn", "photo": {"prefix": "https://irs3.4sqi.net/img/user/", "suffix": "/OCYMLBV1WLVUDZBG.jpg"}}, "updatedAt": 1380525849, "type": "others", "id": "5242a24b11d266b610116370", "canonicalUrl": "https://foursquare.com/deutschebahn/list/wlan-bahnh%C3%B6fe", "name": "WLAN Bahnh\u00f6fe"}], "type": "others", "name": "Lists from other people"}]}, "canonicalUrl": "https://foursquare.com/v/berlin-hauptbahnhof/4a1c8506f964a520457b1fe3", "tags": ["photobooth", "railway", "railway station", "train", "train station"], "storeId": "", "friendVisits": {"count": 2, "items": [{"liked": false, "disliked": false, "user": {"gender": "none", "firstName": "Tam\u00e1s", "relationship": "friend", "photo": {"prefix": "https://irs2.4sqi.net/img/user/", "suffix": "/CH5ADEG1QNZ13SOV.jpg"}, "lastName": "Vir\u00e1g", "id": "5139470"}, "visitedCount": 1}, {"liked": false, "disliked": false, "user": {"gender": "male", "firstName": "Bal\u00e1zs", "relationship": "friend", "photo": {"prefix": "https://irs3.4sqi.net/img/user/", "suffix": "/1665842-HPONRFM4R1CAOHPO.jpg"}, "lastName": "Dob\u00f3", "id": "1665842"}, "visitedCount": 1}], "summary": "2 friends have been here"}, "photos": {"count": 4514, "groups": [{"count": 4514, "items": [{"suffix": "/23032970_kQYriOqBNw8NU0Egwqcks1q78w-uI9goy8RCUh7IeHU.jpg", "width": 612, "visibility": "public", "height": 612, "source": {"url": "http://instagram.com", "name": "Instagram"}, "prefix": "https://irs2.4sqi.net/img/general/", "user": {"lastName": "Litvina", "photo": {"prefix": "https://irs1.4sqi.net/img/user/", "suffix": "/5HR2KE2BGXF5DPZ1.jpg"}, "id": "23032970", "firstName": "\u2708Anastasia", "gender": "female"}, "id": "518120fd498e80d1180cb26e", "createdAt": 1367417085}, {"suffix": "/119329_g2zVJM0q9czTcF-QUdoibQPdrxqZTUDSng7KSg92jUg.jpg", "width": 612, "visibility": "public", "height": 612, "source": {"url": "http://instagram.com", "name": "Instagram"}, "prefix": "https://irs2.4sqi.net/img/general/", "user": {"lastName": "Noeding", "photo": {"prefix": "https://irs0.4sqi.net/img/user/", "suffix": "/5CU34RT41K45SYKQ.jpg"}, "id": "119329", "firstName": "Tom", "gender": "male"}, "id": "51869e6f498e95d7f810ad4a", "createdAt": 1367776879}, {"suffix": "/48758934_FXYuxZzTiZMQmYzoR3cXbkGPfhkmFo7sRx92dFHH-yE.jpg", "width": 574, "visibility": "public", "height": 960, "source": {"url": "https://foursquare.com/download/#/android", "name": "foursquare for Android"}, "prefix": "https://irs1.4sqi.net/img/general/", "user": {"lastName": "Marinova", "photo": {"prefix": "https://irs0.4sqi.net/img/user/", "suffix": "/CSELP3OUNPELC1LR.jpg"}, "id": "48758934", "firstName": "Victoria", "gender": "female"}, "id": "51933b73498ec8ee78c2d1a0", "createdAt": 1368603507}, {"suffix": "/828261_W6b9dDOQd_lkIljLbuvEq19JMiK3FE-h8Dssg52wJfs.jpg", "width": 612, "visibility": "public", "height": 612, "source": {"url": "http://instagram.com", "name": "Instagram"}, "prefix": "https://irs1.4sqi.net/img/general/", "user": {"lastName": "Haupt", "photo": {"prefix": "https://irs1.4sqi.net/img/user/", "suffix": "/JYVM3AVO4ZR2XYMU.jpg"}, "id": "828261", "firstName": "Hans", "gender": "male"}, "id": "51e59160498e26ccb6ddd7e4", "createdAt": 1373999456}, {"suffix": "/42733060_Lj4CP5pveaXuSEj8IAk-UJVDUGaB5LBbZ0j7-bpITdw.jpg", "width": 720, "visibility": "public", "height": 720, "source": {"url": "https://foursquare.com/download/#/iphone", "name": "foursquare for iPhone"}, "prefix": "https://irs1.4sqi.net/img/general/", "user": {"lastName": "G.", "photo": {"prefix": "https://irs0.4sqi.net/img/user/", "suffix": "/BATDMMFSKUTSCDWZ.jpg"}, "id": "42733060", "firstName": "Marc", "gender": "male"}, "id": "5273bdec11d29d354ca50eec", "createdAt": 1383316972}, {"suffix": "/3219150_YgZmvmHUucAkoP4kyFwWkVqHRM_GOdcgjHYHI4Po54E.jpg", "width": 612, "visibility": "public", "height": 612, "source": {"url": "http://instagram.com", "name": "Instagram"}, "prefix": "https://irs0.4sqi.net/img/general/", "user": {"gender": "male", "id": "3219150", "firstName": "Off-The-Path.com", "photo": {"prefix": "https://irs0.4sqi.net/img/user/", "suffix": "/ELFZRX4P51W3QMRN.jpg"}}, "id": "516e7a9de4b0870e33d78ec6", "createdAt": 1366194845}], "type": "venue", "name": "Venue photos"}]}, "attributes": {"groups": [{"count": 4, "items": [{"displayValue": "Yes (incl. American Express & MasterCard)", "displayName": "Credit Cards"}], "type": "payments", "name": "Credit Cards", "summary": "Credit Cards"}, {"count": 1, "items": [{"displayValue": "Free & Paid", "displayName": "Wi-Fi"}], "type": "wifi", "name": "Wi-Fi", "summary": "Free & Paid Wi-Fi"}]}, "stats": {"tipCount": 284, "checkinsCount": 128218, "usersCount": 33877}, "tips": {"count": 284, "groups": [{"count": 284, "items": [{"lang": "de", "todo": {"count": 0}, "canonicalUrl": "https://foursquare.com/item/4b62a37970c603bb110e91b4", "text": "Unter Zeitdruck niemals die Aufz\u00fcge nutzen!", "user": {"lastName": "M\u00f6ller", "photo": {"prefix": "https://irs0.4sqi.net/img/user/", "suffix": "/111740-RV0AJSJITPEW1KCT.jpg"}, "id": "111740", "firstName": "Patrick", "gender": "male"}, "logView": true, "likes": {"count": 155, "groups": [{"count": 155, "items": [], "type": "others"}], "summary": "155 likes"}, "type": "user", "id": "4b62a37970c603bb110e91b4", "createdAt": 1264755577, "like": false}, {"lang": "de", "todo": {"count": 0}, "canonicalUrl": "https://foursquare.com/item/4e5dd289d1640a5975c2175f", "text": "Auf der Rolltreppe gilt: Rechts stehen, Links gehen.", "user": {"lastName": "Kutschera", "photo": {"prefix": "https://irs1.4sqi.net/img/user/", "suffix": "/151343-MZFT5UFLR3CWEDEF.jpg"}, "id": "151343", "firstName": "Jan", "gender": "male"}, "logView": true, "likes": {"count": 101, "groups": [{"count": 101, "items": [], "type": "others"}], "summary": "101 likes"}, "type": "user", "id": "4e5dd289d1640a5975c2175f", "createdAt": 1314771593, "like": false}, {"lang": "en", "todo": {"count": 3}, "canonicalUrl": "https://foursquare.com/item/4d8882fc401a224b550b7918", "text": "It big. It's cold and t has a pizza hut.", "user": {"lastName": "Burke", "photo": {"prefix": "https://irs0.4sqi.net/img/user/", "suffix": "/RO54VJVIANLJFADL.jpg"}, "id": "626428", "firstName": "Donald", "gender": "male"}, "logView": true, "likes": {"count": 79, "groups": [{"count": 79, "items": [], "type": "others"}], "summary": "79 likes"}, "type": "user", "id": "4d8882fc401a224b550b7918", "createdAt": 1300792060, "like": false}, {"lang": "de", "todo": {"count": 6}, "canonicalUrl": "https://foursquare.com/item/4da9537b93a04642f063a21d", "text": "Mit Kleinkind unterwegs? Wickelraum und Spielecke gibt es bei der Bahnhofsmission. Funktioniert.", "user": {"lastName": "Dietrich", "photo": {"prefix": "https://irs3.4sqi.net/img/user/", "suffix": "/DSW4WRNSB10W5C4H.jpg"}, "id": "161184", "firstName": "Sven", "gender": "male"}, "logView": true, "likes": {"count": 62, "groups": [{"count": 62, "items": [], "type": "others"}], "summary": "62 likes"}, "type": "user", "id": "4da9537b93a04642f063a21d", "createdAt": 1302942587, "like": false}, {"lang": "en", "todo": {"count": 11}, "canonicalUrl": "https://foursquare.com/item/4ae5f98070c603bb19b78eb4", "text": "Try to take the U55 to Brandenburger Tor, a decadent ride.", "user": {"lastName": "Friedrich Hartmann", "photo": {"prefix": "https://irs2.4sqi.net/img/user/", "suffix": "/79108_1257149266868.png"}, "id": "79108", "firstName": "Max", "gender": "male"}, "logView": true, "likes": {"count": 60, "groups": [{"count": 60, "items": [], "type": "others"}], "summary": "60 likes"}, "type": "user", "id": "4ae5f98070c603bb19b78eb4", "createdAt": 1256585600, "like": false}, {"lang": "de", "todo": {"count": 1}, "canonicalUrl": "https://foursquare.com/item/50c08175e4b06f3d185a9955", "photourl": "https://irs3.4sqi.net/img/general/original/21669589_ZsdwAt05j4qI-wn0b4hsPtOy_A8qwTMNg-MWQ-AQhjM.jpg", "url": "http://www.berlin.de/orte/sehenswuerdigkeiten/hauptbahnhof/", "text": "Interessantes: Zentral gelegen am touristischen Regierungsviertel entlang der Spree er\u00f6ffnete am 26. Mai 2006 der neu gebaute Berliner Hauptbahnhof. Er ist der gr\u00f6\u00dfte Kreuzungsbahnhof Europas.", "user": {"gender": "none", "type": "chain", "id": "21669589", "firstName": "Deutsche Bahn", "photo": {"prefix": "https://irs3.4sqi.net/img/user/", "suffix": "/OCYMLBV1WLVUDZBG.jpg"}}, "logView": true, "likes": {"count": 46, "groups": [{"count": 46, "items": [], "type": "others"}], "summary": "46 likes"}, "photo": {"suffix": "/21669589_ZsdwAt05j4qI-wn0b4hsPtOy_A8qwTMNg-MWQ-AQhjM.jpg", "width": 929, "height": 622, "source": {"url": "https://foursquare.com", "name": "foursquare Web"}, "prefix": "https://irs3.4sqi.net/img/general/", "id": "50c081778aca5b2ab21499dd", "createdAt": 1354793335}, "type": "user", "id": "50c08175e4b06f3d185a9955", "createdAt": 1354793333, "like": false}, {"lang": "en", "todo": {"count": 3}, "canonicalUrl": "https://foursquare.com/item/4ea8502030f897d8db5bed1a", "text": "Berlin Hauptbahnhof station formerly known as \"Lehrter Stadtbahnhof\"", "user": {"lastName": "Arndt", "photo": {"prefix": "https://irs0.4sqi.net/img/user/", "suffix": "/ZCWTOY1TOLPDVNL1.jpg"}, "id": "8327795", "firstName": "Matthias", "gender": "male"}, "logView": true, "likes": {"count": 46, "groups": [{"count": 46, "items": [], "type": "others"}], "summary": "46 likes"}, "type": "user", "id": "4ea8502030f897d8db5bed1a", "createdAt": 1319653408, "like": false}, {"lang": "de", "todo": {"count": 1}, "canonicalUrl": "https://foursquare.com/item/4e453c47483b03d090cf115c", "text": "Hauptbahnhof? Pfffft. Ich fahr weiter zum Ostbahnhof.", "user": {"gender": "male", "id": "419393", "firstName": "DennyRamone", "photo": {"prefix": "https://irs0.4sqi.net/img/user/", "suffix": "/BHYNO3FYNLOXOHNY.jpg"}}, "logView": true, "likes": {"count": 30, "groups": [{"count": 30, "items": [], "type": "others"}], "summary": "30 likes"}, "type": "user", "id": "4e453c47483b03d090cf115c", "createdAt": 1313160263, "like": false}, {"lang": "en", "todo": {"count": 3}, "canonicalUrl": "https://foursquare.com/item/4b35edce70c603bb51978fb4", "text": "The Apotheke is open 24h here in case you need some medications or other medically necessary supplies during a holiday.", "user": {"lastName": "Farr", "photo": {"prefix": "https://irs3.4sqi.net/img/user/", "suffix": "/-K5XRDF4OSWCUMMS3.jpg"}, "id": "12472", "firstName": "Nick", "gender": "male"}, "logView": true, "likes": {"count": 29, "groups": [{"count": 29, "items": [], "type": "others"}], "summary": "29 likes"}, "type": "user", "id": "4b35edce70c603bb51978fb4", "createdAt": 1261825486, "like": false}, {"lang": "de", "todo": {"count": 0}, "canonicalUrl": "https://foursquare.com/item/510bbfefe4b0809a77ae154c", "photourl": "https://irs3.4sqi.net/img/general/original/21669589_9_aYlg7mnr_GfNu05Xe8DuBDaqNkimXo7kkBsOmSRWA.gif", "text": "Werden Sie \u201eMayor\u201c von Berlin Hauptbahnhof. Die B\u00fcrgermeister von 40 ausgew\u00e4hlten Bahnh\u00f6fen finden Sie auch hier: www.facebook.com/deutschebahn!", "user": {"gender": "none", "type": "chain", "id": "21669589", "firstName": "Deutsche Bahn", "photo": {"prefix": "https://irs3.4sqi.net/img/user/", "suffix": "/OCYMLBV1WLVUDZBG.jpg"}}, "logView": true, "entities": [{"indices": [114, 143], "object": {"url": "http://www.facebook.com/deutschebahn"}, "type": "url"}], "likes": {"count": 25, "groups": [{"count": 25, "items": [], "type": "others"}], "summary": "25 likes"}, "photo": {"suffix": "/21669589_9_aYlg7mnr_GfNu05Xe8DuBDaqNkimXo7kkBsOmSRWA.gif", "width": 200, "height": 200, "source": {"url": "https://foursquare.com", "name": "foursquare Web"}, "prefix": "https://irs3.4sqi.net/img/general/", "id": "510bbff0f31ce60d568641dc", "createdAt": 1359724528}, "type": "user", "id": "510bbfefe4b0809a77ae154c", "createdAt": 1359724527, "like": false}, {"lang": "de", "todo": {"count": 0}, "canonicalUrl": "https://foursquare.com/item/5232e2a511d2694df9755dc1", "photourl": "https://irs0.4sqi.net/img/general/original/721726_Y-Sxl9Cfe8qMQNVPv45qTOB5u_aCbO_W6bYTfl7Wsno.jpg", "photo": {"suffix": "/721726_Y-Sxl9Cfe8qMQNVPv45qTOB5u_aCbO_W6bYTfl7Wsno.jpg", "width": 720, "height": 960, "source": {"url": "https://foursquare.com/download/#/iphone", "name": "foursquare for iPhone"}, "prefix": "https://irs0.4sqi.net/img/general/", "id": "5232e2a711d235a0013d9b4c", "createdAt": 1379066535}, "user": {"gender": "none", "id": "721726", "firstName": "J\u00f6ran", "photo": {"prefix": "https://irs0.4sqi.net/img/user/", "suffix": "/SRMTT34YJBLD2M0P.jpg"}}, "logView": true, "likes": {"count": 22, "groups": [{"count": 22, "items": [], "type": "others"}], "summary": "22 likes"}, "text": "#Protipp: F\u00fcr Menschen, die auf Smartphones starren, gibt es diese Bodenmarkierungen, damit man beim Laufen nicht auf die Gleise f\u00e4llt.", "type": "user", "id": "5232e2a511d2694df9755dc1", "createdAt": 1379066533, "like": false}, {"lang": "de", "todo": {"count": 0}, "canonicalUrl": "https://foursquare.com/item/50095ce2e4b0375edd7b4334", "text": "Berlin, Berlin ... Hey! ... Dein Herz kennt keine Mauern.", "user": {"lastName": "A.", "photo": {"prefix": "https://irs1.4sqi.net/img/user/", "suffix": "/-KUQSK2CFFE5WEBAD.jpg"}, "id": "84752", "firstName": "Tillmann", "gender": "male"}, "logView": true, "likes": {"count": 20, "groups": [{"count": 20, "items": [], "type": "others"}], "summary": "20 likes"}, "type": "user", "id": "50095ce2e4b0375edd7b4334", "createdAt": 1342790882, "like": false}, {"lang": "de", "todo": {"count": 1}, "canonicalUrl": "https://foursquare.com/item/4dc24f8422717802a723e8db", "text": "Starbucks im OG nat\u00fcrlich!", "user": {"lastName": "Weidemann", "photo": {"prefix": "https://irs3.4sqi.net/img/user/", "suffix": "/45STGXWFQMR55SGJ.jpg"}, "id": "1144367", "firstName": "Teut", "gender": "male"}, "logView": true, "likes": {"count": 20, "groups": [{"count": 20, "items": [], "type": "others"}], "summary": "20 likes"}, "type": "user", "id": "4dc24f8422717802a723e8db", "createdAt": 1304579972, "like": false}, {"lang": "en", "todo": {"count": 0}, "canonicalUrl": "https://foursquare.com/item/4d92131e09196a3178ed4ebd", "text": "Angekommen...", "user": {"lastName": "Julia Jung", "photo": {"prefix": "https://irs2.4sqi.net/img/user/", "suffix": "/BMZU5V0QDJPGQJSD.jpg"}, "id": "2611521", "firstName": "Oceanwide", "gender": "female"}, "logView": true, "likes": {"count": 20, "groups": [{"count": 20, "items": [], "type": "others"}], "summary": "20 likes"}, "type": "user", "id": "4d92131e09196a3178ed4ebd", "createdAt": 1301418782, "like": false}, {"lang": "de", "todo": {"count": 1}, "canonicalUrl": "https://foursquare.com/item/50b9f3a0e4b09b57e74aebbc", "photourl": "https://irs0.4sqi.net/img/general/original/21669589_OhOFLPZegTaPXmCIuLBCbG1WxAGF_EiToxOUJeymBWA.jpg", "url": "http://www.bahn.de/p/view/service/1klasse/lounge.shtml", "text": "DB Lounge: Im Berliner Hauptbahnhof verf\u00fcgt die DB Lounge \u00fcber einen getrennten 1. Klasse-Bereich. Sie ist jeden Tag von 7 bis 21 Uhr f\u00fcr Sie ge\u00f6ffnet.", "user": {"gender": "none", "type": "chain", "id": "21669589", "firstName": "Deutsche Bahn", "photo": {"prefix": "https://irs3.4sqi.net/img/user/", "suffix": "/OCYMLBV1WLVUDZBG.jpg"}}, "logView": true, "likes": {"count": 19, "groups": [{"count": 19, "items": [], "type": "others"}], "summary": "19 likes"}, "photo": {"suffix": "/21669589_OhOFLPZegTaPXmCIuLBCbG1WxAGF_EiToxOUJeymBWA.jpg", "width": 929, "height": 622, "source": {"url": "https://foursquare.com", "name": "foursquare Web"}, "prefix": "https://irs0.4sqi.net/img/general/", "id": "50b9f3a670438517a74ece61", "createdAt": 1354363814}, "type": "user", "id": "50b9f3a0e4b09b57e74aebbc", "createdAt": 1354363808, "like": false}, {"lang": "de", "todo": {"count": 1}, "canonicalUrl": "https://foursquare.com/item/4ec002d40e019a162adb4a64", "text": "Einfach weiterfahern zum Ostbahnhof.", "user": {"gender": "male", "id": "419393", "firstName": "DennyRamone", "photo": {"prefix": "https://irs0.4sqi.net/img/user/", "suffix": "/BHYNO3FYNLOXOHNY.jpg"}}, "logView": true, "likes": {"count": 19, "groups": [{"count": 19, "items": [], "type": "others"}], "summary": "19 likes"}, "type": "user", "id": "4ec002d40e019a162adb4a64", "createdAt": 1321206484, "like": false}, {"lang": "en", "todo": {"count": 1}, "canonicalUrl": "https://foursquare.com/item/4e71fa22ae6067986eb313ad", "text": "amazing architecture", "user": {"gender": "male", "id": "299784", "firstName": "shinnygogo", "photo": {"prefix": "https://irs1.4sqi.net/img/user/", "suffix": "/PAOBWQ21WZSKP3L3.jpg"}}, "logView": true, "likes": {"count": 18, "groups": [{"count": 18, "items": [], "type": "others"}], "summary": "18 likes"}, "type": "user", "id": "4e71fa22ae6067986eb313ad", "createdAt": 1316092450, "like": false}, {"lang": "de", "todo": {"count": 0}, "canonicalUrl": "https://foursquare.com/item/4cc1ac6243646dcb2f25478c", "text": "WC kostet mittlerweile 80 Cent!!! Dann lieber wo anders!!!", "user": {"lastName": "Kleine", "photo": {"prefix": "https://irs3.4sqi.net/img/user/", "suffix": "/TOBUVPY1APSZ1N4Q.jpg"}, "id": "497020", "firstName": "Patrick", "gender": "male"}, "logView": true, "likes": {"count": 18, "groups": [{"count": 18, "items": [], "type": "others"}], "summary": "18 likes"}, "type": "user", "id": "4cc1ac6243646dcb2f25478c", "createdAt": 1287760994, "like": false}, {"lang": "en", "todo": {"count": 0}, "canonicalUrl": "https://foursquare.com/item/4f16c386e4b0804e8f9fefdf", "text": "It is huge, indeed. But somehow it seems so calm and peaceful and silent as if it was at a small city. Amazing.", "user": {"lastName": "C.", "photo": {"prefix": "https://irs0.4sqi.net/img/user/", "suffix": "/SN23DW0HI0LYPH0B.jpg"}, "id": "5838822", "firstName": "Luciana", "gender": "female"}, "logView": true, "likes": {"count": 16, "groups": [{"count": 16, "items": [], "type": "others"}], "summary": "16 likes"}, "type": "user", "id": "4f16c386e4b0804e8f9fefdf", "createdAt": 1326891910, "like": false}, {"lang": "de", "todo": {"count": 4}, "canonicalUrl": "https://foursquare.com/item/4cc09469668db60cbd7a0eb4", "text": "kauf keine Blumen bei Blume2000. geh zu Blumen r\u00f6ver im 1.og. besser, freundlicher, preiswerter", "user": {"lastName": "K\u00fchne", "photo": {"prefix": "https://irs2.4sqi.net/img/user/", "suffix": "/2TSQDGA3EUGMQWWM.png"}, "id": "86686", "firstName": "Fr\u00e4nzi", "gender": "female"}, "logView": true, "likes": {"count": 16, "groups": [{"count": 16, "items": [], "type": "others"}], "summary": "16 likes"}, "type": "user", "id": "4cc09469668db60cbd7a0eb4", "createdAt": 1287689321, "like": false}], "type": "others", "name": "Tips from others"}]}, "categories": [{"pluralName": "Train Stations", "primary": true, "name": "Train Station", "shortName": "Train Station", "id": "4bf58dd8d48988d129951735", "icon": {"prefix": "https://ss1.4sqi.net/img/categories_v2/travel/trainstation_", "suffix": ".png"}}, {"shortName": "Subway", "pluralName": "Subways", "id": "4bf58dd8d48988d1fd931735", "icon": {"prefix": "https://ss1.4sqi.net/img/categories_v2/travel/subway_", "suffix": ".png"}, "name": "Subway"}, {"shortName": "Light Rail", "pluralName": "Light Rails", "id": "4bf58dd8d48988d1fc931735", "icon": {"prefix": "https://ss1.4sqi.net/img/categories_v2/travel/lightrail_", "suffix": ".png"}, "name": "Light Rail"}], "name": "Berlin Hauptbahnhof", "like": false, "url": "http://www.bahnhof.de", "phrases": [{"sample": {"entities": [{"indices": [22, 36], "type": "keyPhrase"}], "text": "... die Menschen fast auf die Gleise wegen der Minibahnsteige."}, "phrase": "auf die gleise", "count": 2}, {"sample": {"entities": [{"indices": [0, 15], "type": "keyPhrase"}], "text": "Der Bahnhof ist viel sch\u00f6ner als der Hamburger!"}, "phrase": "der bahnhof ist", "count": 2}, {"sample": {"entities": [{"indices": [14, 27], "type": "keyPhrase"}], "text": "Nie, nie, nie in den Aufzug steigen. Der hat ein Eigenleben und stellt..."}, "phrase": "in den aufzug", "count": 2}], "specials": {"count": 0, "items": []}, "contact": {"phone": "+491805996633", "facebookUsername": "deutschebahn", "facebook": "298026420216364", "formattedPhone": "+49 180 5 996633", "facebookName": "Deutsche Bahn Konzern"}, "ratingSignals": 10819, "popular": {"status": "Likely open", "timeframes": [{"segments": [], "open": [{"renderedTime": "7:00 AM\u201311:00 AM"}, {"renderedTime": "4:00 PM\u20139:00 PM"}], "days": "Today", "includesToday": true}, {"segments": [], "open": [{"renderedTime": "7:00 AM\u201311:00 AM"}, {"renderedTime": "1:00 PM\u20138:00 PM"}], "days": "Wed"}, {"segments": [], "open": [{"renderedTime": "7:00 AM\u20139:00 PM"}], "days": "Thu"}, {"segments": [], "open": [{"renderedTime": "8:00 AM\u201310:00 PM"}], "days": "Fri"}, {"segments": [], "open": [{"renderedTime": "9:00 AM\u20135:00 PM"}], "days": "Sat"}, {"segments": [], "open": [{"renderedTime": "Noon\u201310:00 PM"}], "days": "Sun"}, {"segments": [], "open": [{"renderedTime": "7:00 AM\u20138:00 PM"}], "days": "Mon"}], "isOpen": true}, "timeZone": "Europe/Berlin", "page": {"pageInfo": {"banner": "https://is1.4sqi.net/userpix/VGO30TLJQHNYCG1A.jpg", "description": "Impressum: http://www.deutschebahn.com/de/impressum", "links": {"count": 1, "items": [{"url": "http://www.bahnhof.de"}]}}, "user": {"bio": "", "firstName": "Deutsche Bahn", "gender": "none", "lists": {"groups": [{"count": 5, "items": [], "type": "created"}]}, "homeCity": "Frankfurt, Deutschland", "contact": {"facebook": "298026420216364"}, "followers": {"count": 4227, "groups": []}, "photo": {"prefix": "https://irs3.4sqi.net/img/user/", "suffix": "/OCYMLBV1WLVUDZBG.jpg"}, "tips": {"count": 335}, "type": "chain", "id": "21669589"}}}}}